whologin/__init__.py
whologin/api.py
whologin/api_async.py
whologin/profile_builder.py
whologin/core/__init__.py
whologin/core/api_client.py
whologin/core/async_api_client.py
whologin/core/error.py
whologin-1.1.0.dist-info/METADATA
whologin-1.1.0.dist-info/WHEEL
whologin-1.1.0.dist-info/top_level.txt
whologin-1.1.0.dist-info/RECORD
