Metadata-Version: 2.4
Name: whologin
Version: 1.1.0
Summary: WhoLogin Python SDK
Author: WhoLogin Team
License-Expression: MIT
Project-URL: Homepage, https://github.com/whologinapp/python
Classifier: Programming Language :: Python :: 3
Classifier: Programming Language :: Python :: 3 :: Only
Classifier: Programming Language :: Python :: 3.8
Classifier: Programming Language :: Python :: 3.9
Classifier: Programming Language :: Python :: 3.10
Classifier: Programming Language :: Python :: 3.11
Classifier: Programming Language :: Python :: 3.12
Classifier: Operating System :: OS Independent
Requires-Python: >=3.8
Requires-Dist: httpx>=0.24
